README.txt
setup.py
collective/__init__.py
collective.portlet.skype.egg-info/PKG-INFO
collective.portlet.skype.egg-info/SOURCES.txt
collective.portlet.skype.egg-info/dependency_links.txt
collective.portlet.skype.egg-info/entry_points.txt
collective.portlet.skype.egg-info/namespace_packages.txt
collective.portlet.skype.egg-info/not-zip-safe
collective.portlet.skype.egg-info/requires.txt
collective.portlet.skype.egg-info/top_level.txt
collective/portlet/__init__.py
collective/portlet/skype/__init__.py
collective/portlet/skype/configure.zcml
collective/portlet/skype/fetcher.py
collective/portlet/skype/interfaces.py
collective/portlet/skype/portlet.py
collective/portlet/skype/skype.js
collective/portlet/skype/skype.pt
